LICENSE.md
README.md
pyproject.toml
src/khalib/__init__.py
src/khalib/main.py
src/khalib.egg-info/PKG-INFO
src/khalib.egg-info/SOURCES.txt
src/khalib.egg-info/dependency_links.txt
src/khalib.egg-info/requires.txt
src/khalib.egg-info/top_level.txt