Metadata-Version: 2.4
Name: khalib
Version: 0.3
Summary: Classifier Calibration with Khiops
Author-email: Felipe Olmos <luisfelipe.olmosmarchant@orange.com>
License-Expression: BSD-3-Clause
Project-URL: homepage, https://khiopslab.github.io/khalib
Project-URL: source, https://github.com/KhiopsLab/khalib
Project-URL: tracker, https://github.com/KhiopsLab/khalib/issues
Project-URL: changelog, https://github.com/KhiopsLab/khalib/blob/main/CHANGELOG.md
Classifier: Intended Audience :: Science/Research
Classifier: Intended Audience :: Developers
Classifier: Programming Language :: Python
Classifier: Topic :: Software Development
Classifier: Topic :: Scientific/Engineering
Classifier: Development Status :: 5 - Production/Stable
Classifier: Operating System :: Microsoft :: Windows
Classifier: Operating System :: POSIX
Classifier: Operating System :: Unix
Classifier: Operating System :: MacOS
Classifier: Programming Language :: Python :: 3
Classifier: Programming Language :: Python :: 3.11
Classifier: Programming Language :: Python :: 3.12
Classifier: Programming Language :: Python :: 3.13
Classifier: Programming Language :: Python :: 3.14
Requires-Python: >=3.11
License-File: LICENSE.md
Requires-Dist: khiops>=11.0.0.0
Requires-Dist: numpy>=2.0.0
Requires-Dist: scikit-learn>=1.5.0
Requires-Dist: matplotlib>=3.9.0
Dynamic: license-file
